rknn_toolkit_lite2-2.3.0.dist-info/RECORD
rknn_toolkit_lite2-2.3.0.dist-info/top_level.txt
rknn_toolkit_lite2-2.3.0.dist-info/WHEEL
rknn_toolkit_lite2-2.3.0.dist-info/METADATA
rknnlite/VERSION
rknnlite/__init__.py
rknnlite/utils/__init__.py
rknnlite/utils/yaml_parser.cpython-37m-aarch64-linux-gnu.so
rknnlite/config/cpu_npu_mapper.yml
rknnlite/api/rknn_lite.py
rknnlite/api/rknn_log.cpython-37m-aarch64-linux-gnu.so
rknnlite/api/rknn_runtime.cpython-37m-aarch64-linux-gnu.so
rknnlite/api/rknn_perf.cpython-37m-aarch64-linux-gnu.so
rknnlite/api/__init__.py
rknnlite/api/rknn_utils.cpython-37m-aarch64-linux-gnu.so
rknnlite/api/rknn_model.cpython-37m-aarch64-linux-gnu.so
rknnlite/api/rknn_platform_utils.cpython-37m-aarch64-linux-gnu.so
rknnlite/api/npu_config/__init__.py
rknnlite/api/npu_config/cpu_npu_mapper.cpython-37m-aarch64-linux-gnu.so
