Metadata-Version: 2.1
Name: rknn-toolkit-lite2
Version: 2.3.0
Summary: Rockchip Neural Network Toolkit Lite2. (commit: 27e2f01)
Home-page: https://github.com/airockchip/rknn-toolkit2/tree/master/rknn-toolkit-lite2
Author: ai@rock-chips.com
Author-email: ai@rock-chips.com
Classifier: Programming Language :: Python :: 3
Classifier: Operating System :: OS Independent
Requires-Dist: numpy
Requires-Dist: psutil
Requires-Dist: ruamel.yaml
